AUTHORS
COPYING
LICENSE
MANIFEST.in
README.rst
askbot_requirements.txt
ez_setup.py
setup.py
tox.ini
askbot/__init__.py
askbot/admin.py
askbot/api.py
askbot/apps.py
askbot/auth.py
askbot/context.py
askbot/exceptions.py
askbot/feed.py
askbot/forms.py
askbot/search_indexes.py
askbot/signals.py
askbot/sitemap.py
askbot/startup_procedures.py
askbot/tasks.py
askbot/urls.py
askbot/bin/__init__.py
askbot/bin/checklocales.py
askbot/bin/dos2unix.sh
askbot/bin/generate_modules.py
askbot/bin/mergelocales.py
askbot/bin/rebuildlocales.py
askbot/bin/show_profile_stats.py
askbot/bin/test_permission_assertions
askbot/conf/README
askbot/conf/__init__.py
askbot/conf/access_control.py
askbot/conf/badges.py
askbot/conf/email.py
askbot/conf/email_text.py
askbot/conf/external_keys.py
askbot/conf/feedback.py
askbot/conf/flatpages.py
askbot/conf/forum_data_rules.py
askbot/conf/group_settings.py
askbot/conf/karma_and_badges_visibility.py
askbot/conf/ldap.py
askbot/conf/leading_sidebar.py
askbot/conf/license.py
askbot/conf/login_providers.py
askbot/conf/markup.py
askbot/conf/minimum_reputation.py
askbot/conf/moderation.py
askbot/conf/question_lists.py
askbot/conf/reputation_changes.py
askbot/conf/settings_wrapper.py
askbot/conf/sidebar_main.py
askbot/conf/sidebar_profile.py
askbot/conf/sidebar_question.py
askbot/conf/site_modes.py
askbot/conf/site_settings.py
askbot/conf/skin_general_settings.py
askbot/conf/social_sharing.py
askbot/conf/spam_and_moderation.py
askbot/conf/static_settings.py
askbot/conf/super_groups.py
askbot/conf/user_settings.py
askbot/conf/vote_rules.py
askbot/conf/words.py
askbot/const/__init__.py
askbot/const/message_keys.py
askbot/cron/README
askbot/cron/askbot_cron_job
askbot/deployment/__init__.py
askbot/deployment/assertions.py
askbot/deployment/messages.py
askbot/deployment/package_utils.py
askbot/deployment/path_utils.py
askbot/deployment/template_loader.py
askbot/deps/README
askbot/deps/__init__.py
askbot/deps/django_authopenid/README
sch_askbot.egg-info/PKG-INFO
sch_askbot.egg-info/SOURCES.txt
sch_askbot.egg-info/dependency_links.txt
sch_askbot.egg-info/entry_points.txt
sch_askbot.egg-info/requires.txt
sch_askbot.egg-info/top_level.txt
