Metadata-Version: 1.1
Name: sch-askbot
Version: 1.0.1
Summary: Question and Answer forum, like StackOverflow, written in python and Django
Home-page: http://askbot.org
Author: Evgeny.Fadeev
Author-email: evgeny.fadeev@gmail.com
License: GPLv3
Keywords: forum,community,wiki,Q&A
Platform: UNKNOWN
Classifier: Development Status :: 4 - Beta
Classifier: Environment :: Web Environment
Classifier: Framework :: Django
Classifier: Intended Audience :: Developers
Classifier: License :: OSI Approved :: GNU General Public License (GPL)
Classifier: Natural Language :: English
Classifier: Natural Language :: Finnish
Classifier: Natural Language :: German
Classifier: Natural Language :: Russian
Classifier: Natural Language :: Serbian
Classifier: Natural Language :: Turkish
Classifier: Operating System :: OS Independent
Classifier: Programming Language :: Python :: 2.5
Classifier: Programming Language :: Python :: 2.6
Classifier: Programming Language :: Python :: 2.7
Classifier: Programming Language :: JavaScript
Classifier: Topic :: Communications :: Usenet News
Classifier: Topic :: Communications :: Email :: Mailing List Servers
Classifier: Topic :: Communications
Classifier: Topic :: Internet :: WWW/HTTP :: WSGI :: Application
